{
  "siteName": "Global Innovation Exchange",
  "htmlClass": "",
  "bodyClass": "",
  "contentType": "",
  "pageTitle": "Page Title",
  "url": "#",
  "title": "Title",
  "summary": "<p>This is the summary, which can contain <abbr title='Hyper Text Markup Language'>HTML</abbr> markup. It should be 600 characters or less.</p>",
  "img": {
    "icon": {
      "src": "http://fpoimg.com/48x48?text=Icon",
      "alt": "Icon"
    },
    "thumbnail": {
      "src": "http://fpoimg.com/140x105?text=Thumbnail 4:3",
      "alt": "Thumbnail 4:3"
    },
    "portrait": {
      "src": "http://fpoimg.com/300x400?text=Portrait 3:4",
      "alt": "Portrait 3:4"
    },
    "landscape": {
      "src": "http://fpoimg.com/800x450?text=Landscape 16:9",
      "alt": "Landscape 16:9"
    },
    "profile": {
      "src": "http://fpoimg.com/78x78?text=Square 1:1",
      "alt": "Square 1:1"
    },
    "card": {
      "src": "http://fpoimg.com/500x300?text=Card 5:3",
      "alt": "Card 5:3"
    }
  },
  "user": {
    "name": "Sherlock Holmes",
    "org" : "Scotland Yard",
    "title": "Consulting Detective",
    "location": "London, England",
    "motto": "How often have I said to you that when you have eliminated the impossible, whatever remains, however improbable, must be the truth?",
    "img-500-300": {
      "src": "../../images-patternlab/sherlock-500-300.jpg",
      "alt": "Card 5:3"
    },
    "img-178-178": {
      "src": "../../images-patternlab/sherlock-178-178.jpg",
      "alt": "Card 1:1"
    },
    "img-78-78": {
      "src": "../../images-patternlab/sherlock-78-78.jpg",
      "alt": "Card 1:1"
    },
    "img-58-58": {
      "src": "../../images-patternlab/sherlock-58-58.jpg",
      "alt": "Card 1:1"
    },
    "img-35-35": {
      "src": "../../images-patternlab/sherlock-35-35.jpg",
      "alt": "Card 1:1"
    }
  },
  "year": {
    "long": "2015",
    "short": "15"
  },
  "month": {
    "long": "February",
    "short": "Feb",
    "digit": "2"
  },
  "weekday": {
    "long": "Monday",
    "short": "Mon"
  },
  "day": {
    "long": "10",
    "short": "10",
    "ordinal": "th"
  },
  "hour": {
    "long": "01",
    "short": "1",
    "military": "13",
    "ampm": "pm"
  },
  "minute": {
    "long": "20",
    "short": "20"
  },
  "seconds": "31",
  "funding": "10,000",
  "comments": "10",
  "favorites": "10",
  "evidence": "10",
  "funders": "10",
  "assistance": "10",
  "innovations": "10",
  "resources": "10",
  "members": "10"
}
